libname/__init__.py
libname/hello.py
testpkg123-0.0.1.dist-info/METADATA
testpkg123-0.0.1.dist-info/WHEEL
testpkg123-0.0.1.dist-info/top_level.txt
testpkg123-0.0.1.dist-info/RECORD
