Metadata-Version: 2.1
Name: testpkg123
Version: 0.0.1
Summary: Hello package
Home-page: UNKNOWN
Author: srishti-seth
Author-email: <srishti.seth@hpe.com>
License: UNKNOWN
Keywords: python,hello
Platform: UNKNOWN
Classifier: Development Status :: 1 - Planning
Classifier: Intended Audience :: Developers
Classifier: Programming Language :: Python :: 3
Classifier: Operating System :: Unix
Classifier: Operating System :: MacOS :: MacOS X
Classifier: Operating System :: Microsoft :: Windows
